[
  {
    "symbol": "1INCHUSDT",
    "price_data": {
      "symbol": "1INCHUSDT",
      "price_usd": 0.2554,
      "price_vnd": 6694.095296,
      "volume_24h": 3624207.3,
      "change_24h_percent": -0.7,
      "change_24h_usd": -0.0018,
      "high_24h": 0.2608,
      "low_24h": 0.2532,
      "timestamp": "2025-09-17 13:34:01.654011",
      "source": "binance",
      "usd_vnd_rate": 26210.24
    },
    "ml_features": {
      "symbol": "1INCHUSDT",
      "timestamp": "2025-09-17 13:34:01.654011",
      "close": 0.2554,
      "volume": 3624207.3,
      "high": 0.2608,
      "low": 0.2532,
      "change_24h_percent": -0.7,
      "price_vnd": 6694.095296,
      "usd_vnd_rate": 26210.24,
      "ma_10": 0.25656,
      "ma_50": 0.256198,
      "volatility": 0.48605615607105157,
      "returns": -0.03913894324852896,
      "price_change_1h": -0.03913894324852798,
      "hour": 20
    },
    "klines_count": 100,
    "collection_timestamp": "2025-09-17 13:34:01.788414",
    "status": "success"
  },
  {
    "symbol": "AAVEUSDT",
    "price_data": {
      "symbol": "AAVEUSDT",
      "price_usd": 294.6,
      "price_vnd": 7721536.704000001,
      "volume_24h": 104056.204,
      "change_24h_percent": -0.54,
      "change_24h_usd": -1.6,
      "high_24h": 301.85,
      "low_24h": 289.48,
      "timestamp": "2025-09-17 13:34:02.124121",
      "source": "binance",
      "usd_vnd_rate": 26210.24
    },
    "ml_features": {
      "symbol": "AAVEUSDT",
      "timestamp": "2025-09-17 13:34:02.124121",
      "close": 294.6,
      "volume": 104056.204,
      "high": 301.85,
      "low": 289.48,
      "change_24h_percent": -0.54,
      "price_vnd": 7721536.704000001,
      "usd_vnd_rate": 26210.24,
      "ma_10": 296.168,
      "ma_50": 296.973,
      "volatility": 0.5076987160211809,
      "returns": -0.22353180247915994,
      "price_change_1h": -0.2235318024791601,
      "hour": 20
    },
    "klines_count": 100,
    "collection_timestamp": "2025-09-17 13:34:02.241394",
    "status": "success"
  },
  {
    "symbol": "ADAUSDT",
    "price_data": {
      "symbol": "ADAUSDT",
      "price_usd": 0.872,
      "price_vnd": 22855.32928,
      "volume_24h": 90171937.0,
      "change_24h_percent": -0.011,
      "change_24h_usd": -0.0001,
      "high_24h": 0.8872,
      "low_24h": 0.8566,
      "timestamp": "2025-09-17 13:34:02.563591",
      "source": "binance",
      "usd_vnd_rate": 26210.24
    },
    "ml_features": {
      "symbol": "ADAUSDT",
      "timestamp": "2025-09-17 13:34:02.563591",
      "close": 0.872,
      "volume": 90171937.0,
      "high": 0.8872,
      "low": 0.8566,
      "change_24h_percent": -0.011,
      "price_vnd": 22855.32928,
      "usd_vnd_rate": 26210.24,
      "ma_10": 0.8747199999999999,
      "ma_50": 0.869118,
      "volatility": 0.42478274428088697,
      "returns": 0.05737234652896106,
      "price_change_1h": 0.05737234652896671,
      "hour": 20
    },
    "klines_count": 100,
    "collection_timestamp": "2025-09-17 13:34:02.685586",
    "status": "success"
  },
  {
    "symbol": "ALGOUSDT",
    "price_data": {
      "symbol": "ALGOUSDT",
      "price_usd": 0.2349,
      "price_vnd": 6156.785376000001,
      "volume_24h": 24895606.0,
      "change_24h_percent": -1.178,
      "change_24h_usd": -0.0028,
      "high_24h": 0.2401,
      "low_24h": 0.2332,
      "timestamp": "2025-09-17 13:34:03.017608",
      "source": "binance",
      "usd_vnd_rate": 26210.24
    },
    "ml_features": {
      "symbol": "ALGOUSDT",
      "timestamp": "2025-09-17 13:34:03.017608",
      "close": 0.2349,
      "volume": 24895606.0,
      "high": 0.2401,
      "low": 0.2332,
      "change_24h_percent": -1.178,
      "price_vnd": 6156.785376000001,
      "usd_vnd_rate": 26210.24,
      "ma_10": 0.23576999999999998,
      "ma_50": 0.234678,
      "volatility": 0.4951476316510617,
      "returns": 0.04258943781940694,
      "price_change_1h": 0.04258943781941609,
      "hour": 20
    },
    "klines_count": 100,
    "collection_timestamp": "2025-09-17 13:34:03.140157",
    "status": "success"
  },
  {
    "symbol": "ATOMUSDT",
    "price_data": {
      "symbol": "ATOMUSDT",
      "price_usd": 4.496,
      "price_vnd": 117841.23904000001,
      "volume_24h": 1307117.98,
      "change_24h_percent": 0.201,
      "change_24h_usd": 0.009,
      "high_24h": 4.573,
      "low_24h": 4.44,
      "timestamp": "2025-09-17 13:34:03.471897",
      "source": "binance",
      "usd_vnd_rate": 26210.24
    },
    "ml_features": {
      "symbol": "ATOMUSDT",
      "timestamp": "2025-09-17 13:34:03.471897",
      "close": 4.496,
      "volume": 1307117.98,
      "high": 4.573,
      "low": 4.44,
      "change_24h_percent": 0.201,
      "price_vnd": 117841.23904000001,
      "usd_vnd_rate": 26210.24,
      "ma_10": 4.505,
      "ma_50": 4.5009,
      "volatility": 0.3993976175628218,
      "returns": 0.15593673423925924,
      "price_change_1h": 0.15593673423926402,
      "hour": 20
    },
    "klines_count": 100,
    "collection_timestamp": "2025-09-17 13:34:03.588966",
    "status": "success"
  },
  {
    "symbol": "AVAXUSDT",
    "price_data": {
      "symbol": "AVAXUSDT",
      "price_usd": 29.79,
      "price_vnd": 780803.0496,
      "volume_24h": 2759912.98,
      "change_24h_percent": -2.007,
      "change_24h_usd": -0.61,
      "high_24h": 30.45,
      "low_24h": 29.53,
      "timestamp": "2025-09-17 13:34:03.925059",
      "source": "binance",
      "usd_vnd_rate": 26210.24
    },
    "ml_features": {
      "symbol": "AVAXUSDT",
      "timestamp": "2025-09-17 13:34:03.925059",
      "close": 29.79,
      "volume": 2759912.98,
      "high": 30.45,
      "low": 29.53,
      "change_24h_percent": -2.007,
      "price_vnd": 780803.0496,
      "usd_vnd_rate": 26210.24,
      "ma_10": 29.917999999999996,
      "ma_50": 29.796,
      "volatility": 0.5571256980319892,
      "returns": -0.16756032171582058,
      "price_change_1h": -0.16756032171582008,
      "hour": 20
    },
    "klines_count": 100,
    "collection_timestamp": "2025-09-17 13:34:04.046867",
    "status": "success"
  },
  {
    "symbol": "BALUSDT",
    "price_data": {
      "symbol": "BALUSDT",
      "price_usd": 0.967,
      "price_vnd": 25345.30208,
      "volume_24h": 239235.66,
      "change_24h_percent": -3.685,
      "change_24h_usd": -0.037,
      "high_24h": 1.004,
      "low_24h": 0.921,
      "timestamp": "2025-09-17 13:34:04.376551",
      "source": "binance",
      "usd_vnd_rate": 26210.24
    },
    "ml_features": {
      "symbol": "BALUSDT",
      "timestamp": "2025-09-17 13:34:04.376551",
      "close": 0.967,
      "volume": 239235.66,
      "high": 1.004,
      "low": 0.921,
      "change_24h_percent": -3.685,
      "price_vnd": 25345.30208,
      "usd_vnd_rate": 26210.24,
      "ma_10": 0.9648999999999999,
      "ma_50": 0.934,
      "volatility": 5.4340666467352445,
      "returns": 2.11193241816261,
      "price_change_1h": 2.111932418162621,
      "hour": 20
    },
    "klines_count": 100,
    "collection_timestamp": "2025-09-17 13:34:04.499530",
    "status": "success"
  },
  {
    "symbol": "BCHUSDT",
    "price_data": {
      "symbol": "BCHUSDT",
      "price_usd": 599.3,
      "price_vnd": 15707796.832,
      "volume_24h": 33870.754,
      "change_24h_percent": 1.284,
      "change_24h_usd": 7.6,
      "high_24h": 603.1,
      "low_24h": 589.7,
      "timestamp": "2025-09-17 13:34:04.826492",
      "source": "binance",
      "usd_vnd_rate": 26210.24
    },
    "ml_features": {
      "symbol": "BCHUSDT",
      "timestamp": "2025-09-17 13:34:04.826492",
      "close": 599.3,
      "volume": 33870.754,
      "high": 603.1,
      "low": 589.7,
      "change_24h_percent": 1.284,
      "price_vnd": 15707796.832,
      "usd_vnd_rate": 26210.24,
      "ma_10": 599.76,
      "ma_50": 595.684,
      "volatility": 0.2974413240276981,
      "returns": 0.033383408445986085,
      "price_change_1h": 0.03338340844599095,
      "hour": 20
    },
    "klines_count": 100,
    "collection_timestamp": "2025-09-17 13:34:04.948090",
    "status": "success"
  },
  {
    "symbol": "BNBUSDT",
    "price_data": {
      "symbol": "BNBUSDT",
      "price_usd": 951.91,
      "price_vnd": 24949789.5584,
      "volume_24h": 333356.448,
      "change_24h_percent": 2.389,
      "change_24h_usd": 22.21,
      "high_24h": 963.0,
      "low_24h": 921.94,
      "timestamp": "2025-09-17 13:34:05.276343",
      "source": "binance",
      "usd_vnd_rate": 26210.24
    },
    "ml_features": {
      "symbol": "BNBUSDT",
      "timestamp": "2025-09-17 13:34:05.276343",
      "close": 951.91,
      "volume": 333356.448,
      "high": 963.0,
      "low": 921.94,
      "change_24h_percent": 2.389,
      "price_vnd": 24949789.5584,
      "usd_vnd_rate": 26210.24,
      "ma_10": 953.399,
      "ma_50": 936.7862,
      "volatility": 0.5026147010057266,
      "returns": 0.019963645151444,
      "price_change_1h": 0.01996364515145481,
      "hour": 20
    },
    "klines_count": 100,
    "collection_timestamp": "2025-09-17 13:34:05.394329",
    "status": "success"
  },
  {
    "symbol": "BTCUSDT",
    "price_data": {
      "symbol": "BTCUSDT",
      "price_usd": 116199.99,
      "price_vnd": 3045629625.8976,
      "volume_24h": 12681.13642,
      "change_24h_percent": 0.704,
      "change_24h_usd": 812.77,
      "high_24h": 117286.73,
      "low_24h": 114737.11,
      "timestamp": "2025-09-17 13:34:05.721982",
      "source": "binance",
      "usd_vnd_rate": 26210.24
    },
    "ml_features": {
      "symbol": "BTCUSDT",
      "timestamp": "2025-09-17 13:34:05.721982",
      "close": 116199.99,
      "volume": 12681.13642,
      "high": 117286.73,
      "low": 114737.11,
      "change_24h_percent": 0.704,
      "price_vnd": 3045629625.8976,
      "usd_vnd_rate": 26210.24,
      "ma_10": 116625.075,
      "ma_50": 115871.18179999999,
      "volatility": 0.23615888066059573,
      "returns": -0.004259715636867334,
      "price_change_1h": -0.004259715636871452,
      "hour": 20
    },
    "klines_count": 100,
    "collection_timestamp": "2025-09-17 13:34:05.843452",
    "status": "success"
  },
  {
    "symbol": "COMPUSDT",
    "price_data": {
      "symbol": "COMPUSDT",
      "price_usd": 44.25,
      "price_vnd": 1159803.12,
      "volume_24h": 41537.17,
      "change_24h_percent": -0.584,
      "change_24h_usd": -0.26,
      "high_24h": 45.03,
      "low_24h": 43.8,
      "timestamp": "2025-09-17 13:34:06.173675",
      "source": "binance",
      "usd_vnd_rate": 26210.24
    },
    "ml_features": {
      "symbol": "COMPUSDT",
      "timestamp": "2025-09-17 13:34:06.173675",
      "close": 44.25,
      "volume": 41537.17,
      "high": 45.03,
      "low": 43.8,
      "change_24h_percent": -0.584,
      "price_vnd": 1159803.12,
      "usd_vnd_rate": 26210.24,
      "ma_10": 44.286,
      "ma_50": 44.293800000000005,
      "volatility": 0.4245502040347157,
      "returns": -0.13540961408260443,
      "price_change_1h": -0.135409614082605,
      "hour": 20
    },
    "klines_count": 100,
    "collection_timestamp": "2025-09-17 13:34:06.288092",
    "status": "success"
  },
  {
    "symbol": "CRVUSDT",
    "price_data": {
      "symbol": "CRVUSDT",
      "price_usd": 0.7276,
      "price_vnd": 19070.570624000004,
      "volume_24h": 28729543.1,
      "change_24h_percent": -0.356,
      "change_24h_usd": -0.0026,
      "high_24h": 0.74,
      "low_24h": 0.7147,
      "timestamp": "2025-09-17 13:34:06.616084",
      "source": "binance",
      "usd_vnd_rate": 26210.24
    },
    "ml_features": {
      "symbol": "CRVUSDT",
      "timestamp": "2025-09-17 13:34:06.616084",
      "close": 0.7276,
      "volume": 28729543.1,
      "high": 0.74,
      "low": 0.7147,
      "change_24h_percent": -0.356,
      "price_vnd": 19070.570624000004,
      "usd_vnd_rate": 26210.24,
      "ma_10": 0.7274700000000001,
      "ma_50": 0.735552,
      "volatility": 0.6920750895423391,
      "returns": -0.3969883641341543,
      "price_change_1h": -0.39698836413415656,
      "hour": 20
    },
    "klines_count": 100,
    "collection_timestamp": "2025-09-17 13:34:06.731255",
    "status": "success"
  },
  {
    "symbol": "DENTUSDT",
    "price_data": {
      "symbol": "DENTUSDT",
      "price_usd": 0.000737,
      "price_vnd": 19.316946880000003,
      "volume_24h": 508689442.0,
      "change_24h_percent": -0.54,
      "change_24h_usd": -4e-06,
      "high_24h": 0.000754,
      "low_24h": 0.000731,
      "timestamp": "2025-09-17 13:34:07.066616",
      "source": "binance",
      "usd_vnd_rate": 26210.24
    },
    "ml_features": {
      "symbol": "DENTUSDT",
      "timestamp": "2025-09-17 13:34:07.066616",
      "close": 0.000737,
      "volume": 508689442.0,
      "high": 0.000754,
      "low": 0.000731,
      "change_24h_percent": -0.54,
      "price_vnd": 19.316946880000003,
      "usd_vnd_rate": 26210.24,
      "ma_10": 0.0007399,
      "ma_50": 0.0007366400000000001,
      "volatility": 0.4788232433746127,
      "returns": 0.13586956521738358,
      "price_change_1h": 0.1358695652173946,
      "hour": 20
    },
    "klines_count": 100,
    "collection_timestamp": "2025-09-17 13:34:07.181203",
    "status": "success"
  },
  {
    "symbol": "DOGEUSDT",
    "price_data": {
      "symbol": "DOGEUSDT",
      "price_usd": 0.2669,
      "price_vnd": 6995.513056000001,
      "volume_24h": 1648656186.0,
      "change_24h_percent": 0.372,
      "change_24h_usd": 0.00099,
      "high_24h": 0.27204,
      "low_24h": 0.257,
      "timestamp": "2025-09-17 13:34:07.512805",
      "source": "binance",
      "usd_vnd_rate": 26210.24
    },
    "ml_features": {
      "symbol": "DOGEUSDT",
      "timestamp": "2025-09-17 13:34:07.512805",
      "close": 0.2669,
      "volume": 1648656186.0,
      "high": 0.27204,
      "low": 0.257,
      "change_24h_percent": 0.372,
      "price_vnd": 6995.513056000001,
      "usd_vnd_rate": 26210.24,
      "ma_10": 0.266744,
      "ma_50": 0.2664568,
      "volatility": 0.5586471946502126,
      "returns": 0.0524816314290133,
      "price_change_1h": 0.05248163142901072,
      "hour": 20
    },
    "klines_count": 100,
    "collection_timestamp": "2025-09-17 13:34:07.626649",
    "status": "success"
  },
  {
    "symbol": "DOTUSDT",
    "price_data": {
      "symbol": "DOTUSDT",
      "price_usd": 4.193,
      "price_vnd": 109899.53632,
      "volume_24h": 5577271.25,
      "change_24h_percent": -0.804,
      "change_24h_usd": -0.034,
      "high_24h": 4.295,
      "low_24h": 4.151,
      "timestamp": "2025-09-17 13:34:07.944830",
      "source": "binance",
      "usd_vnd_rate": 26210.24
    },
    "ml_features": {
      "symbol": "DOTUSDT",
      "timestamp": "2025-09-17 13:34:07.944830",
      "close": 4.193,
      "volume": 5577271.25,
      "high": 4.295,
      "low": 4.151,
      "change_24h_percent": -0.804,
      "price_vnd": 109899.53632,
      "usd_vnd_rate": 26210.24,
      "ma_10": 4.1956,
      "ma_50": 4.1951,
      "volatility": 0.5242522681208845,
      "returns": 0.071599045346038,
      "price_change_1h": 0.07159904534604357,
      "hour": 20
    },
    "klines_count": 100,
    "collection_timestamp": "2025-09-17 13:34:08.056846",
    "status": "success"
  },
  {
    "symbol": "DYDXUSDT",
    "price_data": {
      "symbol": "DYDXUSDT",
      "price_usd": 0.6206,
      "price_vnd": 16266.074944000002,
      "volume_24h": 3488215.18,
      "change_24h_percent": -0.273,
      "change_24h_usd": -0.0017,
      "high_24h": 0.6364,
      "low_24h": 0.6098,
      "timestamp": "2025-09-17 13:34:08.393796",
      "source": "binance",
      "usd_vnd_rate": 26210.24
    },
    "ml_features": {
      "symbol": "DYDXUSDT",
      "timestamp": "2025-09-17 13:34:08.393796",
      "close": 0.6206,
      "volume": 3488215.18,
      "high": 0.6364,
      "low": 0.6098,
      "change_24h_percent": -0.273,
      "price_vnd": 16266.074944000002,
      "usd_vnd_rate": 26210.24,
      "ma_10": 0.6231000000000001,
      "ma_50": 0.619476,
      "volatility": 0.5483846142746743,
      "returns": 0.11292143894177098,
      "price_change_1h": 0.11292143894177026,
      "hour": 20
    },
    "klines_count": 100,
    "collection_timestamp": "2025-09-17 13:34:08.516843",
    "status": "success"
  },
  {
    "symbol": "ETCUSDT",
    "price_data": {
      "symbol": "ETCUSDT",
      "price_usd": 20.38,
      "price_vnd": 534164.6912,
      "volume_24h": 543022.3,
      "change_24h_percent": -0.196,
      "change_24h_usd": -0.04,
      "high_24h": 20.61,
      "low_24h": 20.1,
      "timestamp": "2025-09-17 13:34:08.845994",
      "source": "binance",
      "usd_vnd_rate": 26210.24
    },
    "ml_features": {
      "symbol": "ETCUSDT",
      "timestamp": "2025-09-17 13:34:08.845994",
      "close": 20.38,
      "volume": 543022.3,
      "high": 20.61,
      "low": 20.1,
      "change_24h_percent": -0.196,
      "price_vnd": 534164.6912,
      "usd_vnd_rate": 26210.24,
      "ma_10": 20.381999999999998,
      "ma_50": 20.3998,
      "volatility": 0.3660929777592217,
      "returns": -0.09803921568627416,
      "price_change_1h": -0.09803921568627243,
      "hour": 20
    },
    "klines_count": 100,
    "collection_timestamp": "2025-09-17 13:34:08.961488",
    "status": "success"
  },
  {
    "symbol": "ETHUSDT",
    "price_data": {
      "symbol": "ETHUSDT",
      "price_usd": 4497.97,
      "price_vnd": 117892873.21280001,
      "volume_24h": 354750.9847,
      "change_24h_percent": -0.147,
      "change_24h_usd": -6.64,
      "high_24h": 4557.67,
      "low_24h": 4424.0,
      "timestamp": "2025-09-17 13:34:09.282238",
      "source": "binance",
      "usd_vnd_rate": 26210.24
    },
    "ml_features": {
      "symbol": "ETHUSDT",
      "timestamp": "2025-09-17 13:34:09.282238",
      "close": 4497.97,
      "volume": 354750.9847,
      "high": 4557.67,
      "low": 4424.0,
      "change_24h_percent": -0.147,
      "price_vnd": 117892873.21280001,
      "usd_vnd_rate": 26210.24,
      "ma_10": 4506.403,
      "ma_50": 4504.4744,
      "volatility": 0.43400736944455753,
      "returns": -0.09084730101331928,
      "price_change_1h": -0.09084730101331713,
      "hour": 20
    },
    "klines_count": 100,
    "collection_timestamp": "2025-09-17 13:34:09.396042",
    "status": "success"
  },
  {
    "symbol": "FILUSDT",
    "price_data": {
      "symbol": "FILUSDT",
      "price_usd": 2.496,
      "price_vnd": 65420.759040000004,
      "volume_24h": 11818841.69,
      "change_24h_percent": 1.711,
      "change_24h_usd": 0.042,
      "high_24h": 2.66,
      "low_24h": 2.411,
      "timestamp": "2025-09-17 13:34:09.717982",
      "source": "binance",
      "usd_vnd_rate": 26210.24
    },
    "ml_features": {
      "symbol": "FILUSDT",
      "timestamp": "2025-09-17 13:34:09.717982",
      "close": 2.496,
      "volume": 11818841.69,
      "high": 2.66,
      "low": 2.411,
      "change_24h_percent": 1.711,
      "price_vnd": 65420.759040000004,
      "usd_vnd_rate": 26210.24,
      "ma_10": 2.5211,
      "ma_50": 2.46952,
      "volatility": 0.9911662042753908,
      "returns": -0.3990422984836317,
      "price_change_1h": -0.39904229848363076,
      "hour": 20
    },
    "klines_count": 100,
    "collection_timestamp": "2025-09-17 13:34:09.832602",
    "status": "success"
  },
  {
    "symbol": "HBARUSDT",
    "price_data": {
      "symbol": "HBARUSDT",
      "price_usd": 0.23518,
      "price_vnd": 6164.124243200001,
      "volume_24h": 96495132.0,
      "change_24h_percent": -1.039,
      "change_24h_usd": -0.00247,
      "high_24h": 0.23995,
      "low_24h": 0.23339,
      "timestamp": "2025-09-17 13:34:10.152527",
      "source": "binance",
      "usd_vnd_rate": 26210.24
    },
    "ml_features": {
      "symbol": "HBARUSDT",
      "timestamp": "2025-09-17 13:34:10.152527",
      "close": 0.23518,
      "volume": 96495132.0,
      "high": 0.23995,
      "low": 0.23339,
      "change_24h_percent": -1.039,
      "price_vnd": 6164.124243200001,
      "usd_vnd_rate": 26210.24,
      "ma_10": 0.23575899999999997,
      "ma_50": 0.23580080000000003,
      "volatility": 0.5050959297494977,
      "returns": -0.0764785859959316,
      "price_change_1h": -0.07647858599592687,
      "hour": 20
    },
    "klines_count": 100,
    "collection_timestamp": "2025-09-17 13:34:10.273969",
    "status": "success"
  },
  {
    "symbol": "ICPUSDT",
    "price_data": {
      "symbol": "ICPUSDT",
      "price_usd": 4.707,
      "price_vnd": 123371.59968,
      "volume_24h": 1836140.66,
      "change_24h_percent": -0.106,
      "change_24h_usd": -0.005,
      "high_24h": 4.806,
      "low_24h": 4.636,
      "timestamp": "2025-09-17 13:34:10.603210",
      "source": "binance",
      "usd_vnd_rate": 26210.24
    },
    "ml_features": {
      "symbol": "ICPUSDT",
      "timestamp": "2025-09-17 13:34:10.603210",
      "close": 4.707,
      "volume": 1836140.66,
      "high": 4.806,
      "low": 4.636,
      "change_24h_percent": -0.106,
      "price_vnd": 123371.59968,
      "usd_vnd_rate": 26210.24,
      "ma_10": 4.7141,
      "ma_50": 4.7028,
      "volatility": 0.45590419273603533,
      "returns": 0.0,
      "price_change_1h": 0.0,
      "hour": 20
    },
    "klines_count": 100,
    "collection_timestamp": "2025-09-17 13:34:10.718153",
    "status": "success"
  },
  {
    "symbol": "LINKUSDT",
    "price_data": {
      "symbol": "LINKUSDT",
      "price_usd": 23.04,
      "price_vnd": 603883.9296,
      "volume_24h": 3560807.1,
      "change_24h_percent": -2.082,
      "change_24h_usd": -0.49,
      "high_24h": 23.75,
      "low_24h": 22.75,
      "timestamp": "2025-09-17 13:34:11.042992",
      "source": "binance",
      "usd_vnd_rate": 26210.24
    },
    "ml_features": {
      "symbol": "LINKUSDT",
      "timestamp": "2025-09-17 13:34:11.042992",
      "close": 23.04,
      "volume": 3560807.1,
      "high": 23.75,
      "low": 22.75,
      "change_24h_percent": -2.082,
      "price_vnd": 603883.9296,
      "usd_vnd_rate": 26210.24,
      "ma_10": 23.258000000000003,
      "ma_50": 23.426599999999997,
      "volatility": 0.45083726189910417,
      "returns": 0.26109660574411553,
      "price_change_1h": 0.26109660574411975,
      "hour": 20
    },
    "klines_count": 100,
    "collection_timestamp": "2025-09-17 13:34:11.157861",
    "status": "success"
  },
  {
    "symbol": "LTCUSDT",
    "price_data": {
      "symbol": "LTCUSDT",
      "price_usd": 114.38,
      "price_vnd": 2997927.2512000003,
      "volume_24h": 358793.697,
      "change_24h_percent": -0.114,
      "change_24h_usd": -0.13,
      "high_24h": 115.87,
      "low_24h": 113.2,
      "timestamp": "2025-09-17 13:34:11.478133",
      "source": "binance",
      "usd_vnd_rate": 26210.24
    },
    "ml_features": {
      "symbol": "LTCUSDT",
      "timestamp": "2025-09-17 13:34:11.478133",
      "close": 114.38,
      "volume": 358793.697,
      "high": 115.87,
      "low": 113.2,
      "change_24h_percent": -0.114,
      "price_vnd": 2997927.2512000003,
      "usd_vnd_rate": 26210.24,
      "ma_10": 114.595,
      "ma_50": 114.22800000000001,
      "volatility": 0.3506177528751625,
      "returns": 0.07874704698573876,
      "price_change_1h": 0.07874704698572858,
      "hour": 20
    },
    "klines_count": 100,
    "collection_timestamp": "2025-09-17 13:34:11.596174",
    "status": "success"
  },
  {
    "symbol": "MATICUSDT",
    "price_data": {
      "symbol": "MATICUSDT",
      "price_usd": 0.3794,
      "price_vnd": 9944.165056000002,
      "volume_24h": 2834467.3,
      "change_24h_percent": -0.289,
      "change_24h_usd": -0.0011,
      "high_24h": 0.3806,
      "low_24h": 0.3774,
      "timestamp": "2025-09-17 13:34:11.930082",
      "source": "binance",
      "usd_vnd_rate": 26210.24
    },
    "ml_features": {
      "symbol": "MATICUSDT",
      "timestamp": "2025-09-17 13:34:11.930082",
      "close": 0.3794,
      "volume": 2834467.3,
      "high": 0.3806,
      "low": 0.3774,
      "change_24h_percent": -0.289,
      "price_vnd": 9944.165056000002,
      "usd_vnd_rate": 26210.24,
      "ma_10": 0.38177,
      "ma_50": 0.37573,
      "volatility": 0.6386091489401996,
      "returns": 0.026364355391517158,
      "price_change_1h": 0.026364355391507773,
      "hour": 20
    },
    "klines_count": 100,
    "collection_timestamp": "2025-09-17 13:34:12.053243",
    "status": "success"
  },
  {
    "symbol": "MKRUSDT",
    "price_data": {
      "symbol": "MKRUSDT",
      "price_usd": 1813.7,
      "price_vnd": 47537512.288,
      "volume_24h": 2449.5825,
      "change_24h_percent": -0.022,
      "change_24h_usd": -0.4,
      "high_24h": 1928.0,
      "low_24h": 1780.6,
      "timestamp": "2025-09-17 13:34:12.392139",
      "source": "binance",
      "usd_vnd_rate": 26210.24
    },
    "ml_features": {
      "symbol": "MKRUSDT",
      "timestamp": "2025-09-17 13:34:12.392139",
      "close": 1813.7,
      "volume": 2449.5825,
      "high": 1928.0,
      "low": 1780.6,
      "change_24h_percent": -0.022,
      "price_vnd": 47537512.288,
      "usd_vnd_rate": 26210.24,
      "ma_10": 1821.4900000000002,
      "ma_50": 1818.34,
      "volatility": 0.9860024132243393,
      "returns": 0.32081420432545915,
      "price_change_1h": 0.32081420432545793,
      "hour": 20
    },
    "klines_count": 100,
    "collection_timestamp": "2025-09-17 13:34:12.513670",
    "status": "success"
  },
  {
    "symbol": "RVNUSDT",
    "price_data": {
      "symbol": "RVNUSDT",
      "price_usd": 0.01302,
      "price_vnd": 341.25732480000005,
      "volume_24h": 45156819.0,
      "change_24h_percent": -0.535,
      "change_24h_usd": -7e-05,
      "high_24h": 0.01328,
      "low_24h": 0.0129,
      "timestamp": "2025-09-17 13:34:12.857214",
      "source": "binance",
      "usd_vnd_rate": 26210.24
    },
    "ml_features": {
      "symbol": "RVNUSDT",
      "timestamp": "2025-09-17 13:34:12.857214",
      "close": 0.01302,
      "volume": 45156819.0,
      "high": 0.01328,
      "low": 0.0129,
      "change_24h_percent": -0.535,
      "price_vnd": 341.25732480000005,
      "usd_vnd_rate": 26210.24,
      "ma_10": 0.01304,
      "ma_50": 0.013070400000000003,
      "volatility": 0.36850146117088195,
      "returns": 0.0768639508070601,
      "price_change_1h": 0.07686395080706836,
      "hour": 20
    },
    "klines_count": 100,
    "collection_timestamp": "2025-09-17 13:34:12.972167",
    "status": "success"
  },
  {
    "symbol": "SHIBUSDT",
    "price_data": {
      "symbol": "SHIBUSDT",
      "price_usd": 1.305e-05,
      "price_vnd": 0.34204363200000004,
      "volume_24h": 1199311542409.0,
      "change_24h_percent": -0.153,
      "change_24h_usd": -2e-08,
      "high_24h": 1.326e-05,
      "low_24h": 1.286e-05,
      "timestamp": "2025-09-17 13:34:13.298135",
      "source": "binance",
      "usd_vnd_rate": 26210.24
    },
    "ml_features": {
      "symbol": "SHIBUSDT",
      "timestamp": "2025-09-17 13:34:13.298135",
      "close": 1.305e-05,
      "volume": 1199311542409.0,
      "high": 1.326e-05,
      "low": 1.286e-05,
      "change_24h_percent": -0.153,
      "price_vnd": 0.34204363200000004,
      "usd_vnd_rate": 26210.24,
      "ma_10": 1.3043e-05,
      "ma_50": 1.30668e-05,
      "volatility": 0.4146776983133846,
      "returns": 0.07668711656441118,
      "price_change_1h": 0.07668711656441644,
      "hour": 20
    },
    "klines_count": 100,
    "collection_timestamp": "2025-09-17 13:34:13.415764",
    "status": "success"
  },
  {
    "symbol": "SOLUSDT",
    "price_data": {
      "symbol": "SOLUSDT",
      "price_usd": 235.29,
      "price_vnd": 6167007.3696,
      "volume_24h": 3465057.854,
      "change_24h_percent": 0.081,
      "change_24h_usd": 0.19,
      "high_24h": 240.95,
      "low_24h": 231.26,
      "timestamp": "2025-09-17 13:34:13.744780",
      "source": "binance",
      "usd_vnd_rate": 26210.24
    },
    "ml_features": {
      "symbol": "SOLUSDT",
      "timestamp": "2025-09-17 13:34:13.744780",
      "close": 235.29,
      "volume": 3465057.854,
      "high": 240.95,
      "low": 231.26,
      "change_24h_percent": 0.081,
      "price_vnd": 6167007.3696,
      "usd_vnd_rate": 26210.24,
      "ma_10": 235.204,
      "ma_50": 235.30780000000001,
      "volatility": 0.508637894451692,
      "returns": 0.2129653292443967,
      "price_change_1h": 0.212965329244399,
      "hour": 20
    },
    "klines_count": 100,
    "collection_timestamp": "2025-09-17 13:34:13.867880",
    "status": "success"
  },
  {
    "symbol": "SUSHIUSDT",
    "price_data": {
      "symbol": "SUSHIUSDT",
      "price_usd": 0.7722,
      "price_vnd": 20239.547328,
      "volume_24h": 3771594.7,
      "change_24h_percent": -2.154,
      "change_24h_usd": -0.017,
      "high_24h": 0.7963,
      "low_24h": 0.767,
      "timestamp": "2025-09-17 13:34:14.188568",
      "source": "binance",
      "usd_vnd_rate": 26210.24
    },
    "ml_features": {
      "symbol": "SUSHIUSDT",
      "timestamp": "2025-09-17 13:34:14.188568",
      "close": 0.7722,
      "volume": 3771594.7,
      "high": 0.7963,
      "low": 0.767,
      "change_24h_percent": -2.154,
      "price_vnd": 20239.547328,
      "usd_vnd_rate": 26210.24,
      "ma_10": 0.77698,
      "ma_50": 0.77834,
      "volatility": 0.6152364623476115,
      "returns": -0.12933264355923235,
      "price_change_1h": -0.12933264355923446,
      "hour": 20
    },
    "klines_count": 100,
    "collection_timestamp": "2025-09-17 13:34:14.301376",
    "status": "success"
  },
  {
    "symbol": "TRXUSDT",
    "price_data": {
      "symbol": "TRXUSDT",
      "price_usd": 0.3411,
      "price_vnd": 8940.312864000001,
      "volume_24h": 312721378.9,
      "change_24h_percent": -1.558,
      "change_24h_usd": -0.0054,
      "high_24h": 0.3466,
      "low_24h": 0.3395,
      "timestamp": "2025-09-17 13:34:14.629653",
      "source": "binance",
      "usd_vnd_rate": 26210.24
    },
    "ml_features": {
      "symbol": "TRXUSDT",
      "timestamp": "2025-09-17 13:34:14.629653",
      "close": 0.3411,
      "volume": 312721378.9,
      "high": 0.3466,
      "low": 0.3395,
      "change_24h_percent": -1.558,
      "price_vnd": 8940.312864000001,
      "usd_vnd_rate": 26210.24,
      "ma_10": 0.34123000000000003,
      "ma_50": 0.343412,
      "volatility": 0.27485949005988264,
      "returns": -0.058599472604736746,
      "price_change_1h": -0.058599472604740105,
      "hour": 20
    },
    "klines_count": 100,
    "collection_timestamp": "2025-09-17 13:34:14.750855",
    "status": "success"
  },
  {
    "symbol": "UNIUSDT",
    "price_data": {
      "symbol": "UNIUSDT",
      "price_usd": 9.242,
      "price_vnd": 242235.03808000003,
      "volume_24h": 3132806.24,
      "change_24h_percent": -0.73,
      "change_24h_usd": -0.068,
      "high_24h": 9.405,
      "low_24h": 9.1,
      "timestamp": "2025-09-17 13:34:15.079754",
      "source": "binance",
      "usd_vnd_rate": 26210.24
    },
    "ml_features": {
      "symbol": "UNIUSDT",
      "timestamp": "2025-09-17 13:34:15.079754",
      "close": 9.242,
      "volume": 3132806.24,
      "high": 9.405,
      "low": 9.1,
      "change_24h_percent": -0.73,
      "price_vnd": 242235.03808000003,
      "usd_vnd_rate": 26210.24,
      "ma_10": 9.2688,
      "ma_50": 9.22508,
      "volatility": 0.47601965853625505,
      "returns": -0.01081899816076648,
      "price_change_1h": -0.010818998160764317,
      "hour": 20
    },
    "klines_count": 100,
    "collection_timestamp": "2025-09-17 13:34:15.202133",
    "status": "success"
  },
  {
    "symbol": "VETUSDT",
    "price_data": {
      "symbol": "VETUSDT",
      "price_usd": 0.02415,
      "price_vnd": 632.977296,
      "volume_24h": 250779279.2,
      "change_24h_percent": -0.494,
      "change_24h_usd": -0.00012,
      "high_24h": 0.02467,
      "low_24h": 0.02386,
      "timestamp": "2025-09-17 13:34:15.668495",
      "source": "binance",
      "usd_vnd_rate": 26210.24
    },
    "ml_features": {
      "symbol": "VETUSDT",
      "timestamp": "2025-09-17 13:34:15.668495",
      "close": 0.02415,
      "volume": 250779279.2,
      "high": 0.02467,
      "low": 0.02386,
      "change_24h_percent": -0.494,
      "price_vnd": 632.977296,
      "usd_vnd_rate": 26210.24,
      "ma_10": 0.024293000000000002,
      "ma_50": 0.024243200000000003,
      "volatility": 0.4530657865355478,
      "returns": 0.041425020712515526,
      "price_change_1h": 0.04142502071250867,
      "hour": 20
    },
    "klines_count": 100,
    "collection_timestamp": "2025-09-17 13:34:15.782117",
    "status": "success"
  },
  {
    "symbol": "XLMUSDT",
    "price_data": {
      "symbol": "XLMUSDT",
      "price_usd": 0.3871,
      "price_vnd": 10145.983904,
      "volume_24h": 53956847.0,
      "change_24h_percent": -0.514,
      "change_24h_usd": -0.002,
      "high_24h": 0.3908,
      "low_24h": 0.3796,
      "timestamp": "2025-09-17 13:34:16.113340",
      "source": "binance",
      "usd_vnd_rate": 26210.24
    },
    "ml_features": {
      "symbol": "XLMUSDT",
      "timestamp": "2025-09-17 13:34:16.113340",
      "close": 0.3871,
      "volume": 53956847.0,
      "high": 0.3908,
      "low": 0.3796,
      "change_24h_percent": -0.514,
      "price_vnd": 10145.983904,
      "usd_vnd_rate": 26210.24,
      "ma_10": 0.38514,
      "ma_50": 0.38298599999999994,
      "volatility": 0.4539424880475546,
      "returns": 0.10343935867598297,
      "price_change_1h": 0.10343935867597918,
      "hour": 20
    },
    "klines_count": 100,
    "collection_timestamp": "2025-09-17 13:34:16.234302",
    "status": "success"
  },
  {
    "symbol": "XMRUSDT",
    "price_data": {
      "symbol": "XMRUSDT",
      "price_usd": 118.7,
      "price_vnd": 3111155.4880000004,
      "volume_24h": 5017.379,
      "change_24h_percent": 4.766,
      "change_24h_usd": 5.4,
      "high_24h": 119.6,
      "low_24h": 110.4,
      "timestamp": "2025-09-17 13:34:16.556946",
      "source": "binance",
      "usd_vnd_rate": 26210.24
    },
    "ml_features": {
      "symbol": "XMRUSDT",
      "timestamp": "2025-09-17 13:34:16.556946",
      "close": 118.7,
      "volume": 5017.379,
      "high": 119.6,
      "low": 110.4,
      "change_24h_percent": 4.766,
      "price_vnd": 3111155.4880000004,
      "usd_vnd_rate": 26210.24,
      "ma_10": 112.87,
      "ma_50": 119.156,
      "volatility": 1.4592809249014778,
      "returns": 4.0315512708150925,
      "price_change_1h": 4.031551270815082,
      "hour": 20
    },
    "klines_count": 100,
    "collection_timestamp": "2025-09-17 13:34:16.670957",
    "status": "success"
  }
]